{
  "Timestamp": "2025-11-17 03:44:20",
  "TargetFrameworks": [
    "net8.0",
    "net9.0",
    "net10.0"
  ],
  "Summary": {
    "PackagesChanged": 0,
    "PackagesConfigured": 2,
    "ProjectsUpdated": 2,
    "FrameworksSet": "net8.0;net9.0;net10.0",
    "DirectoryPackagesPropsUpdated": true,
    "FrameworkSpecificGroups": 3
  },
  "PackagesFound": 2,
  "PackageChanges": [],
  "ChangeSummaryText": "No package version changes - this might be a new setup or no updates available",
  "ProjectsFound": 2
}
